psik/__init__.py
psik/backend.py
psik/config.py
psik/console.py
psik/exceptions.py
psik/job.py
psik/logs.py
psik/manager.py
psik/models.py
psik/psik.py
psik/py.typed
psik/statfile.py
psik/web.py
psik/zipstr.py
psik/backends/__init__.py
psik/backends/local.py
psik/backends/nersc.py
psik/backends/slurm.py
psik-3.0.0.dist-info/licenses/LICENSE
psik-3.0.0.dist-info/METADATA
psik-3.0.0.dist-info/WHEEL
psik-3.0.0.dist-info/entry_points.txt
psik-3.0.0.dist-info/top_level.txt
psik-3.0.0.dist-info/RECORD
