Metadata-Version: 2.4
Name: psik
Version: 3.0.0
Summary: Portable Submission Interface for Jobs
Author-email: "David M. Rogers" <predictivestatmech@gmail.com>
License-Expression: BSD-3-Clause
Project-URL: repository, https://github.com/frobnitzem/psik
Requires-Python: <4.0,>=3.9
License-File: LICENSE
Requires-Dist: pydantic<3.0,>=2.1.1
Requires-Dist: typer<1.0,>=0.9
Requires-Dist: anyio<5.0,>=4.0.0
Requires-Dist: importlib-metadata<7.0,>=6.8.0
Requires-Dist: aiohttp<4.0,>=3.8.0
Requires-Dist: pyyaml<7.0,>=6.0.2
Provides-Extra: facilities
Requires-Dist: globus-compute-sdk; extra == "facilities"
Requires-Dist: sfapi_client; extra == "facilities"
Provides-Extra: dev
Requires-Dist: pytest>=6.1.0; extra == "dev"
Requires-Dist: mypy<2.0,>=1.5.1; extra == "dev"
Requires-Dist: pytest-asyncio<2.0,>=1.2.0; extra == "dev"
Requires-Dist: pytest-cov<5.0,>=4.1.0; extra == "dev"
Requires-Dist: pytest-aiohttp<2.0,>=1.0.5; extra == "dev"
Dynamic: license-file
